LICENSE
MANIFEST.in
README.rst
setup.cfg
setup.py
versioneer.py
artellapipe/__init__.py
artellapipe/tools/__init__.py
artellapipe/tools/assetsmanager/__init__.py
artellapipe/tools/assetsmanager/__logging__.ini
artellapipe/tools/assetsmanager/__version__.py
artellapipe/tools/assetsmanager/_version.py
artellapipe/tools/assetsmanager/__pycache__/__init__.cpython-36.pyc
artellapipe/tools/assetsmanager/__pycache__/__version__.cpython-36.pyc
artellapipe/tools/assetsmanager/__pycache__/_version.cpython-36.pyc
artellapipe/tools/assetsmanager/assets/__init__.py
artellapipe/tools/assetsmanager/assets/__pycache__/__init__.cpython-36.pyc
artellapipe/tools/assetsmanager/core/__init__.py
artellapipe/tools/assetsmanager/core/assetsmanager.py
artellapipe/tools/assetsmanager/core/__pycache__/__init__.cpython-36.pyc
artellapipe/tools/assetsmanager/core/__pycache__/assetsmanager.cpython-36.pyc
artellapipe/tools/assetsmanager/resources/icons/color/control_panel.png
artellapipe/tools/assetsmanager/resources/images/assetsmanager_logo.png
artellapipe/tools/assetsmanager/resources/images/no_asset_selected.png
artellapipe/tools/assetsmanager/resources/images/no_sequence_selected.png
artellapipe/tools/assetsmanager/resources/images/no_shot_selected.png
artellapipe/tools/assetsmanager/widgets/__init__.py
artellapipe/tools/assetsmanager/widgets/assetsmanager.py
artellapipe/tools/assetsmanager/widgets/shotswidget.py
artellapipe/tools/assetsmanager/widgets/__pycache__/__init__.cpython-36.pyc
artellapipe/tools/assetsmanager/widgets/__pycache__/assetsmanager.cpython-36.pyc
artellapipe/tools/assetsmanager/widgets/__pycache__/shotswidget.cpython-36.pyc
artellapipe_tools_assetsmanager.egg-info/PKG-INFO
artellapipe_tools_assetsmanager.egg-info/SOURCES.txt
artellapipe_tools_assetsmanager.egg-info/dependency_links.txt
artellapipe_tools_assetsmanager.egg-info/not-zip-safe
artellapipe_tools_assetsmanager.egg-info/requires.txt
artellapipe_tools_assetsmanager.egg-info/top_level.txt
tests/__init__.py
tests/test_general.py