Metadata-Version: 2.1
Name: artellapipe-tools-assetsmanager
Version: 0.0.9
Summary: Tool to easily manage project assets
Home-page: https://github.com/ArtellaPipe/artellapipe-tools-assetsmanager
Author: Tomas Poveda
Author-email: tpovedatd@gmail.com
License: MIT
Platform: UNKNOWN
Provides-Extra: dev
Provides-Extra: test
